{
  "outputFormat": [
    "di",
    "json",
    "csv"
  ],
  "sObjects": [
    {
      "sObject": "contact",
      "language": "en",
      "count": 400,
      "fields": {
        "AccountId": {
          "type": "reference",
          "referenceTo": "Account",
          "values": [],
          "relationshipType": "lookup"
        },
        "LastName": {
          "type": "text"
        },
        "FirstName": {
          "type": "text"
        },
        "Salutation": {
          "type": "picklist",
          "values": [
            "Mr.",
            "Ms.",
            "Mrs.",
            "Dr.",
            "Prof.",
            "Mx."
          ]
        },
        "OtherStreet": {
          "type": "address"
        },
        "OtherCity": {
          "type": "address"
        },
        "OtherState": {
          "type": "address"
        },
        "OtherPostalCode": {
          "type": "address"
        },
        "OtherCountry": {
          "type": "address"
        },
        "OtherLatitude": {
          "type": "double"
        },
        "OtherLongitude": {
          "type": "double"
        },
        "OtherGeocodeAccuracy": {
          "type": "picklist",
          "values": [
            "Address",
            "NearAddress",
            "Block",
            "Street",
            "ExtendedZip",
            "Zip",
            "Neighborhood",
            "City",
            "County",
            "State",
            "Unknown"
          ]
        },
        "MailingStreet": {
          "type": "address"
        },
        "MailingCity": {
          "type": "address"
        },
        "MailingState": {
          "type": "address"
        },
        "MailingPostalCode": {
          "type": "address"
        },
        "MailingCountry": {
          "type": "address"
        },
        "MailingLatitude": {
          "type": "double"
        },
        "MailingLongitude": {
          "type": "double"
        },
        "MailingGeocodeAccuracy": {
          "type": "picklist",
          "values": [
            "Address",
            "NearAddress",
            "Block",
            "Street",
            "ExtendedZip",
            "Zip",
            "Neighborhood",
            "City",
            "County",
            "State",
            "Unknown"
          ]
        },
        "Phone": {
          "type": "phone"
        },
        "Fax": {
          "type": "phone"
        },
        "MobilePhone": {
          "type": "phone"
        },
        "HomePhone": {
          "type": "phone"
        },
        "OtherPhone": {
          "type": "phone"
        },
        "AssistantPhone": {
          "type": "phone"
        },
        "ReportsToId": {
          "type": "reference",
          "referenceTo": "Contact",
          "values": [],
          "relationshipType": "lookup"
        },
        "Email": {
          "type": "email"
        },
        "Title": {
          "type": "text"
        },
        "Department": {
          "type": "text"
        },
        "AssistantName": {
          "type": "text"
        },
        "LeadSource": {
          "type": "picklist",
          "values": [
            "Web",
            "Phone Inquiry",
            "Partner Referral",
            "Purchased List",
            "Other"
          ]
        },
        "Birthdate": {
          "type": "date"
        },
        "Description": {
          "type": "text"
        },
        "OwnerId": {
          "type": "reference",
          "referenceTo": "User",
          "values": [],
          "relationshipType": "master-detail"
        },
        "EmailBouncedReason": {
          "type": "text"
        },
        "EmailBouncedDate": {
          "type": "datetime"
        },
        "IndividualId": {
          "type": "reference",
          "referenceTo": "Individual",
          "values": [],
          "relationshipType": "lookup"
        },
        "ContactSource": {
          "type": "picklist",
          "values": [
            "Auto Create"
          ]
        },
        "Level__c": {
          "type": "picklist",
          "values": [
            "Secondary",
            "Tertiary",
            "Primary"
          ]
        },
        "Languages__c": {
          "type": "text"
        },
        "rooms__HasOptedOutOfRoomNotifications__c": {
          "type": "boolean"
        },
        "rooms__LatestRoomMembership__c": {
          "type": "reference",
          "referenceTo": "rooms__DocumentRoomMember__c",
          "values": [],
          "relationshipType": "lookup"
        },
        "rooms__PortalAccessEnabled__c": {
          "type": "boolean"
        },
        "rooms__PortalLastLoginDate__c": {
          "type": "datetime"
        },
        "rooms__PortalLoginUsername__c": {
          "type": "text"
        },
        "rooms__PortalRegistrationDate__c": {
          "type": "datetime"
        }
      }
    }
  ]
}